pyxel/__init__.py
pyxel/__main__.py
pyxel/_version.py
pyxel/evaluator.py
pyxel/options.py
pyxel/py.typed
pyxel/run.py
pyxel/show_versions.py
pyxel/backends/__init__.py
pyxel/backends/asdf.py
pyxel/backends/hdf5.py
pyxel/calibration/__init__.py
pyxel/calibration/algorithm.py
pyxel/calibration/archipelago.py
pyxel/calibration/archipelago_datatree.py
pyxel/calibration/calibration.py
pyxel/calibration/fitness.py
pyxel/calibration/fitting.py
pyxel/calibration/fitting_datatree.py
pyxel/calibration/protocols.py
pyxel/calibration/user_defined.py
pyxel/calibration/util.py
pyxel/configuration/__init__.py
pyxel/configuration/configuration.py
pyxel/data_structure/__init__.py
pyxel/data_structure/array.py
pyxel/data_structure/charge.py
pyxel/data_structure/image.py
pyxel/data_structure/persistence.py
pyxel/data_structure/phase.py
pyxel/data_structure/photon.py
pyxel/data_structure/pixel.py
pyxel/data_structure/pixel_read.py
pyxel/data_structure/scene.py
pyxel/data_structure/signal.py
pyxel/data_structure/util.py
pyxel/detectors/__init__.py
pyxel/detectors/channels.py
pyxel/detectors/characteristics.py
pyxel/detectors/charge_to_volt_settings.py
pyxel/detectors/detector.py
pyxel/detectors/environment.py
pyxel/detectors/geometry.py
pyxel/detectors/optics.py
pyxel/detectors/readout_properties.py
pyxel/detectors/reference_pixels.py
pyxel/detectors/apd/__init__.py
pyxel/detectors/apd/apd.py
pyxel/detectors/apd/apd_characteristics.py
pyxel/detectors/apd/apd_geometry.py
pyxel/detectors/apd/saphira_characteristics.py
pyxel/detectors/ccd/__init__.py
pyxel/detectors/ccd/ccd.py
pyxel/detectors/ccd/ccd_geometry.py
pyxel/detectors/cmos/__init__.py
pyxel/detectors/cmos/cmos.py
pyxel/detectors/cmos/cmos_geometry.py
pyxel/detectors/mkid/__init__.py
pyxel/detectors/mkid/mkid.py
pyxel/detectors/mkid/mkid_geometry.py
pyxel/exposure/__init__.py
pyxel/exposure/exposure.py
pyxel/exposure/readout.py
pyxel/gui/__init__.py
pyxel/gui/basic_config_ui.py
pyxel/gui/run.py
pyxel/gui/start_gui.py
pyxel_sim-2.16.dist-info/licenses/LICENSE.txt
pyxel_sim-2.16.dist-info/METADATA
pyxel_sim-2.16.dist-info/WHEEL
pyxel_sim-2.16.dist-info/entry_points.txt
pyxel_sim-2.16.dist-info/top_level.txt
pyxel_sim-2.16.dist-info/RECORD
