Metadata-Version: 2.4
Name: pyxel_sim
Version: 2.16
Summary: Pyxel detector simulation framework.
Author-email: The Pyxel development team <pyxel@esa.int>
License-Expression: MIT
Project-URL: homepage, https://esa.gitlab.io/pyxel/
Project-URL: documentation, https://esa.gitlab.io/pyxel/doc/
Project-URL: repository, https://gitlab.com/esa/pyxel
Project-URL: changelog, https://gitlab.com/esa/pyxel/-/releases
Project-URL: tracker, https://gitlab.com/esa/pyxel/issues
Keywords: ESA,data modeling,sensors,calibration,CCD,CMOS,active sensors,electronics
Classifier: Development Status :: 5 - Production/Stable
Classifier: Environment :: Console
Classifier: Intended Audience :: Developers
Classifier: Intended Audience :: Science/Research
Classifier: Operating System :: OS Independent
Classifier: Programming Language :: Python :: 3
Classifier: Programming Language :: Python :: 3.10
Classifier: Programming Language :: Python :: 3.11
Classifier: Programming Language :: Python :: 3.12
Classifier: Programming Language :: Python :: 3.13
Classifier: Programming Language :: Python :: 3.14
Classifier: Topic :: Scientific/Engineering :: Astronomy
Classifier: Topic :: Scientific/Engineering :: Image Processing
Classifier: Topic :: Scientific/Engineering :: Physics
Classifier: Typing :: Typed
Requires-Python: >=3.10
License-File: LICENSE.txt
Requires-Dist: numpy>=2
Requires-Dist: scipy>=1.12
Requires-Dist: pandas[excel]<3,>=2.1
Requires-Dist: xarray[io,parallel,viz]>=2024.10.0
Requires-Dist: astropy>=5.2
Requires-Dist: astroquery
Requires-Dist: specutils>=1.2
Requires-Dist: synphot
Requires-Dist: pyckles
Requires-Dist: scikit-image>=0.23.0
Requires-Dist: numba>=0.56.4
Requires-Dist: hvplot>=0.9
Requires-Dist: fsspec[http]>=2021
Requires-Dist: pympler
Requires-Dist: pillow
Requires-Dist: diskcache
Requires-Dist: rich
Requires-Dist: annotated-types
Provides-Extra: calibration
Requires-Dist: pygmo>=2.16.1; extra == "calibration"
Provides-Extra: model
Requires-Dist: poppy>=1.1.0; extra == "model"
Requires-Dist: lacosmic; extra == "model"
Requires-Dist: photutils; extra == "model"
Provides-Extra: io
Requires-Dist: asdf; extra == "io"
Provides-Extra: all
Requires-Dist: pyxel-sim[calibration]; extra == "all"
Requires-Dist: pyxel-sim[model]; extra == "all"
Requires-Dist: pyxel-sim[io]; extra == "all"
Dynamic: license-file
